tznn/__init__.py
tznn/timezone.json
tznn-0.1.0.dist-info/licenses/LICENSE
tznn-0.1.0.dist-info/METADATA
tznn-0.1.0.dist-info/WHEEL
tznn-0.1.0.dist-info/top_level.txt
tznn-0.1.0.dist-info/RECORD
