Metadata-Version: 2.4
Name: tznn
Version: 0.1.0
Summary: Tiny helpers for IANA time zones and abbreviations
Author-email: tznn <chuongqpvn@gmail.com>
License: MIT License
Project-URL: Homepage, https://example.com/tznn
Project-URL: Issues, https://example.com/tznn/issues
Keywords: timezone,zoneinfo,IANA,abbreviation
Classifier: Programming Language :: Python :: 3
Classifier: Programming Language :: Python :: 3 :: Only
Classifier: License :: OSI Approved :: MIT License
Classifier: Operating System :: OS Independent
Requires-Python: >=3.9
License-File: LICENSE
Requires-Dist: tzdata; platform_system == "Windows"
Dynamic: license-file
